mati/__init__.py
mati/auth.py
mati/client.py
mati/helpers.py
mati/py.typed
mati/version.py
mati/resources/__init__.py
mati/resources/access_tokens.py
mati/resources/base.py
mati/resources/user_verification_data.py
mati/resources/verifications.py
mati/types/__init__.py
mati/types/enums.py
tests/__init__.py
tests/conftest.py
tests/test_client.py
tests/test_types.py
mati-2.0.9.dist-info/LICENSE
mati-2.0.9.dist-info/METADATA
mati-2.0.9.dist-info/WHEEL
mati-2.0.9.dist-info/top_level.txt
mati-2.0.9.dist-info/RECORD
