Metadata-Version: 2.1
Name: mati
Version: 2.0.9
Summary: Client library for mati.io
Home-page: https://github.com/cuenca-mx/mati-python
Author: Cuenca
Author-email: dev@cuenca.com
Classifier: Programming Language :: Python :: 3
Classifier: Programming Language :: Python :: 3.6
Classifier: Programming Language :: Python :: 3.7
Classifier: Programming Language :: Python :: 3.8
Classifier: License :: OSI Approved :: MIT License
Classifier: Operating System :: OS Independent
Requires-Python: >=3.6
License-File: LICENSE
Requires-Dist: requests<3.0.0,>=2.22.0
Requires-Dist: iso8601<0.2.0,>=0.1.12
Requires-Dist: dataclasses>=0.6; python_version < "3.7"
